adafruit_circuitpython_ht16k33-4.6.14.dist-info/licenses/LICENSE
adafruit_ht16k33/__init__.py
adafruit_ht16k33/animations.py
adafruit_ht16k33/bargraph.py
adafruit_ht16k33/ht16k33.py
adafruit_ht16k33/matrix.py
adafruit_ht16k33/segments.py
adafruit_circuitpython_ht16k33-4.6.14.dist-info/METADATA
adafruit_circuitpython_ht16k33-4.6.14.dist-info/WHEEL
adafruit_circuitpython_ht16k33-4.6.14.dist-info/top_level.txt
adafruit_circuitpython_ht16k33-4.6.14.dist-info/RECORD
