Metadata-Version: 2.4
Name: adafruit-circuitpython-ht16k33
Version: 4.6.14
Summary: CircuitPython library for HT16K33 LED matrices and segment displays.
Author-email: Adafruit Industries <circuitpython@adafruit.com>
License: MIT
Project-URL: Homepage, https://github.com/adafruit/Adafruit_CircuitPython_HT16K33
Keywords: adafruit,ht16k33,led,matrix,segment,displays,hardware,micropython,circuitpython
Classifier: Intended Audience :: Developers
Classifier: Topic :: Software Development :: Libraries
Classifier: Topic :: Software Development :: Embedded Systems
Classifier: Topic :: System :: Hardware
Classifier: License :: OSI Approved :: MIT License
Classifier: Programming Language :: Python :: 3
License-File: LICENSE
Requires-Dist: Adafruit-Blinka
Requires-Dist: adafruit-circuitpython-typing~=1.6
Requires-Dist: adafruit-circuitpython-busdevice
Provides-Extra: optional
Requires-Dist: pillow; extra == "optional"
Dynamic: license-file
